{"frames":{"New Piskel0.png":{"frame":{"x":0,"y":0,"w":16,"h":16},"rotated":false,"trimmed":false,"spriteSourceSize":{"x":0,"y":0,"w":16,"h":16},"sourceSize":{"w":16,"h":16}},"New Piskel1.png":{"frame":{"x":16,"y":0,"w":16,"h":16},"rotated":false,"trimmed":false,"spriteSourceSize":{"x":0,"y":0,"w":16,"h":16},"sourceSize":{"w":16,"h":16}},"New Piskel2.png":{"frame":{"x":32,"y":0,"w":16,"h":16},"rotated":false,"trimmed":false,"spriteSourceSize":{"x":0,"y":0,"w":16,"h":16},"sourceSize":{"w":16,"h":16}},"New Piskel3.png":{"frame":{"x":48,"y":0,"w":16,"h":16},"rotated":false,"trimmed":false,"spriteSourceSize":{"x":0,"y":0,"w":16,"h":16},"sourceSize":{"w":16,"h":16}},"New Piskel4.png":{"frame":{"x":64,"y":0,"w":16,"h":16},"rotated":false,"trimmed":false,"spriteSourceSize":{"x":0,"y":0,"w":16,"h":16},"sourceSize":{"w":16,"h":16}},"New Piskel5.png":{"frame":{"x":80,"y":0,"w":16,"h":16},"rotated":false,"trimmed":false,"spriteSourceSize":{"x":0,"y":0,"w":16,"h":16},"sourceSize":{"w":16,"h":16}},"New Piskel6.png":{"frame":{"x":96,"y":0,"w":16,"h":16},"rotated":false,"trimmed":false,"spriteSourceSize":{"x":0,"y":0,"w":16,"h":16},"sourceSize":{"w":16,"h":16}},"New Piskel7.png":{"frame":{"x":112,"y":0,"w":16,"h":16},"rotated":false,"trimmed":false,"spriteSourceSize":{"x":0,"y":0,"w":16,"h":16},"sourceSize":{"w":16,"h":16}},"New Piskel8.png":{"frame":{"x":128,"y":0,"w":16,"h":16},"rotated":false,"trimmed":false,"spriteSourceSize":{"x":0,"y":0,"w":16,"h":16},"sourceSize":{"w":16,"h":16}},"New Piskel9.png":{"frame":{"x":144,"y":0,"w":16,"h":16},"rotated":false,"trimmed":false,"spriteSourceSize":{"x":0,"y":0,"w":16,"h":16},"sourceSize":{"w":16,"h":16}},"New Piskel10.png":{"frame":{"x":160,"y":0,"w":16,"h":16},"rotated":false,"trimmed":false,"spriteSourceSize":{"x":0,"y":0,"w":16,"h":16},"sourceSize":{"w":16,"h":16}},"New Piskel11.png":{"frame":{"x":176,"y":0,"w":16,"h":16},"rotated":false,"trimmed":false,"spriteSourceSize":{"x":0,"y":0,"w":16,"h":16},"sourceSize":{"w":16,"h":16}},"New Piskel12.png":{"frame":{"x":192,"y":0,"w":16,"h":16},"rotated":false,"trimmed":false,"spriteSourceSize":{"x":0,"y":0,"w":16,"h":16},"sourceSize":{"w":16,"h":16}},"New Piskel13.png":{"frame":{"x":208,"y":0,"w":16,"h":16},"rotated":false,"trimmed":false,"spriteSourceSize":{"x":0,"y":0,"w":16,"h":16},"sourceSize":{"w":16,"h":16}},"New Piskel14.png":{"frame":{"x":224,"y":0,"w":16,"h":16},"rotated":false,"trimmed":false,"spriteSourceSize":{"x":0,"y":0,"w":16,"h":16},"sourceSize":{"w":16,"h":16}},"New Piskel15.png":{"frame":{"x":240,"y":0,"w":16,"h":16},"rotated":false,"trimmed":false,"spriteSourceSize":{"x":0,"y":0,"w":16,"h":16},"sourceSize":{"w":16,"h":16}}},"meta":{"app":"https://github.com/piskelapp/piskel/","version":"1.0","image":"New Piskel.png","format":"RGBA8888","size":{"w":256,"h":16}}}