{ "frames": {
   "down_s1": {
    "frame": { "x": 0, "y": 0, "w": 16, "h": 16 },
    "rotated": false,
    "trimmed": false,
    "spriteSourceSize": { "x": 0, "y": 0, "w": 16, "h": 16 },
    "sourceSize": { "w": 16, "h": 16 },
    "duration": 200
   },
   "down_r1": {
    "frame": { "x": 16, "y": 0, "w": 16, "h": 16 },
    "rotated": false,
    "trimmed": false,
    "spriteSourceSize": { "x": 0, "y": 0, "w": 16, "h": 16 },
    "sourceSize": { "w": 16, "h": 16 },
    "duration": 200
   },
   "down_r2": {
    "frame": { "x": 32, "y": 0, "w": 16, "h": 16 },
    "rotated": false,
    "trimmed": false,
    "spriteSourceSize": { "x": 0, "y": 0, "w": 16, "h": 16 },
    "sourceSize": { "w": 16, "h": 16 },
    "duration": 200
   },
   "down_s2": {
    "frame": { "x": 48, "y": 0, "w": 16, "h": 16 },
    "rotated": false,
    "trimmed": false,
    "spriteSourceSize": { "x": 0, "y": 0, "w": 16, "h": 16 },
    "sourceSize": { "w": 16, "h": 16 },
    "duration": 200
   },
   "down_l1": {
    "frame": { "x": 64, "y": 0, "w": 16, "h": 16 },
    "rotated": false,
    "trimmed": false,
    "spriteSourceSize": { "x": 0, "y": 0, "w": 16, "h": 16 },
    "sourceSize": { "w": 16, "h": 16 },
    "duration": 200
   },
   "down_l2": {
    "frame": { "x": 80, "y": 0, "w": 16, "h": 16 },
    "rotated": false,
    "trimmed": false,
    "spriteSourceSize": { "x": 0, "y": 0, "w": 16, "h": 16 },
    "sourceSize": { "w": 16, "h": 16 },
    "duration": 200
   },
   "right_s1": {
    "frame": { "x": 96, "y": 0, "w": 16, "h": 16 },
    "rotated": false,
    "trimmed": false,
    "spriteSourceSize": { "x": 0, "y": 0, "w": 16, "h": 16 },
    "sourceSize": { "w": 16, "h": 16 },
    "duration": 200
   },
   "right_r1": {
    "frame": { "x": 112, "y": 0, "w": 16, "h": 16 },
    "rotated": false,
    "trimmed": false,
    "spriteSourceSize": { "x": 0, "y": 0, "w": 16, "h": 16 },
    "sourceSize": { "w": 16, "h": 16 },
    "duration": 200
   },
   "right_r2": {
    "frame": { "x": 128, "y": 0, "w": 16, "h": 16 },
    "rotated": false,
    "trimmed": false,
    "spriteSourceSize": { "x": 0, "y": 0, "w": 16, "h": 16 },
    "sourceSize": { "w": 16, "h": 16 },
    "duration": 200
   },
   "right_s2": {
    "frame": { "x": 144, "y": 0, "w": 16, "h": 16 },
    "rotated": false,
    "trimmed": false,
    "spriteSourceSize": { "x": 0, "y": 0, "w": 16, "h": 16 },
    "sourceSize": { "w": 16, "h": 16 },
    "duration": 200
   },
   "right_l1": {
    "frame": { "x": 160, "y": 0, "w": 16, "h": 16 },
    "rotated": false,
    "trimmed": false,
    "spriteSourceSize": { "x": 0, "y": 0, "w": 16, "h": 16 },
    "sourceSize": { "w": 16, "h": 16 },
    "duration": 200
   },
   "right_l2": {
    "frame": { "x": 176, "y": 0, "w": 16, "h": 16 },
    "rotated": false,
    "trimmed": false,
    "spriteSourceSize": { "x": 0, "y": 0, "w": 16, "h": 16 },
    "sourceSize": { "w": 16, "h": 16 },
    "duration": 200
   },
   "up_s1": {
    "frame": { "x": 192, "y": 0, "w": 16, "h": 16 },
    "rotated": false,
    "trimmed": false,
    "spriteSourceSize": { "x": 0, "y": 0, "w": 16, "h": 16 },
    "sourceSize": { "w": 16, "h": 16 },
    "duration": 200
   },
   "up_r1": {
    "frame": { "x": 208, "y": 0, "w": 16, "h": 16 },
    "rotated": false,
    "trimmed": false,
    "spriteSourceSize": { "x": 0, "y": 0, "w": 16, "h": 16 },
    "sourceSize": { "w": 16, "h": 16 },
    "duration": 200
   },
   "up_r2": {
    "frame": { "x": 224, "y": 0, "w": 16, "h": 16 },
    "rotated": false,
    "trimmed": false,
    "spriteSourceSize": { "x": 0, "y": 0, "w": 16, "h": 16 },
    "sourceSize": { "w": 16, "h": 16 },
    "duration": 200
   },
   "up_s2": {
    "frame": { "x": 240, "y": 0, "w": 16, "h": 16 },
    "rotated": false,
    "trimmed": false,
    "spriteSourceSize": { "x": 0, "y": 0, "w": 16, "h": 16 },
    "sourceSize": { "w": 16, "h": 16 },
    "duration": 200
   },
   "up_l1": {
    "frame": { "x": 272, "y": 0, "w": 16, "h": 16 },
    "rotated": false,
    "trimmed": false,
    "spriteSourceSize": { "x": 0, "y": 0, "w": 16, "h": 16 },
    "sourceSize": { "w": 16, "h": 16 },
    "duration": 200
   },
   "up_l2": {
    "frame": { "x": 288, "y": 0, "w": 16, "h": 16 },
    "rotated": false,
    "trimmed": false,
    "spriteSourceSize": { "x": 0, "y": 0, "w": 16, "h": 16 },
    "sourceSize": { "w": 16, "h": 16 },
    "duration": 200
   },
   "left_s1": {
    "frame": { "x": 304, "y": 0, "w": 16, "h": 16 },
    "rotated": false,
    "trimmed": false,
    "spriteSourceSize": { "x": 0, "y": 0, "w": 16, "h": 16 },
    "sourceSize": { "w": 16, "h": 16 },
    "duration": 200
   },
   "left_r1": {
    "frame": { "x": 320, "y": 0, "w": 16, "h": 16 },
    "rotated": false,
    "trimmed": false,
    "spriteSourceSize": { "x": 0, "y": 0, "w": 16, "h": 16 },
    "sourceSize": { "w": 16, "h": 16 },
    "duration": 200
   },
   "left_r2": {
    "frame": { "x": 336, "y": 0, "w": 16, "h": 16 },
    "rotated": false,
    "trimmed": false,
    "spriteSourceSize": { "x": 0, "y": 0, "w": 16, "h": 16 },
    "sourceSize": { "w": 16, "h": 16 },
    "duration": 200
   },
   "left_s2": {
    "frame": { "x": 352, "y": 0, "w": 16, "h": 16 },
    "rotated": false,
    "trimmed": false,
    "spriteSourceSize": { "x": 0, "y": 0, "w": 16, "h": 16 },
    "sourceSize": { "w": 16, "h": 16 },
    "duration": 200
   },
   "left_l1": {
    "frame": { "x": 368, "y": 0, "w": 16, "h": 16 },
    "rotated": false,
    "trimmed": false,
    "spriteSourceSize": { "x": 0, "y": 0, "w": 16, "h": 16 },
    "sourceSize": { "w": 16, "h": 16 },
    "duration": 200
   },
   "left_l2": {
    "frame": { "x": 384, "y": 0, "w": 16, "h": 16 },
    "rotated": false,
    "trimmed": false,
    "spriteSourceSize": { "x": 0, "y": 0, "w": 16, "h": 16 },
    "sourceSize": { "w": 16, "h": 16 },
    "duration": 200
   }
 },
 "meta": {
  "app": "https://www.org/",
  "version": "1.2.40-x64",
  "image": "leatherArmor.png",
  "format": "I8",
  "size": { "w": 400, "h": 16 },
  "scale": "1"
 },
 "animations":
 {
    "default":["down_s1"],
    "walkup":["up_r1","up_r2","up_s2","up_s1","up_l1","up_l2","up_s2","up_s1"],
    "walkleft":["left_r1","left_r2","left_s2","left_s1","left_l1","left_l2","left_s2","left_s1"],
    "walkdown":["down_r1","down_r2","down_s2","down_s1","down_l1","down_l2","down_s2","down_s1"],
    "walkright":["right_r1","right_r2","right_s2","right_s1","right_l1","right_l2","right_s2","right_s1"]
 }
}
